{
  "id": "btc-bitcoin",
  "name": "Bitcoin",
  "symbol": "BTC",
  "rank": 1,
  "total_supply": 19980031,
  "max_supply": 21000000,
  "beta_value": 0.86629,
  "first_data_at": "2010-07-17T00:00:00Z",
  "last_updated": "2026-01-24T07:19:28Z",
  "quotes": {
    "USD": {
      "price": 89540.47766298454,
      "volume_24h": 30919167165.05972,
      "volume_24h_change_24h": 3.88,
      "market_cap": 1789022146245,
      "market_cap_change_24h": 0.08,
      "percent_change_15m": -0.02,
      "percent_change_30m": -0.04,
      "percent_change_1h": -0.05,
      "percent_change_6h": 0.14,
      "percent_change_12h": -0.2,
      "percent_change_24h": 0.08,
      "percent_change_7d": -5.9,
      "percent_change_30d": 0.48,
      "percent_change_1y": -14.18,
      "ath_price": 126173.1777846797,
      "ath_date": "2025-10-06T19:00:40Z",
      "percent_from_price_ath": -29.03
    }
  }
}